[{ "team1" : "Augsburg", "team2" : "Bayer Leverkusen", "date" : "Friday, Feb 17 2017", "time" : "19:30", "matchID" : 1091011},{ "team1" : "Eintracht Frankfurt", "team2" : "Ingolstadt", "date" : "Saturday, Feb 18 2017", "time" : "14:30", "matchID" : 1090992},{ "team1" : "Borussia Dortmund", "team2" : "Wolfsburg", "date" : "Saturday, Feb 18 2017", "time" : "14:30", "matchID" : 1090995},{ "team1" : "Mainz 05", "team2" : "Werder Bremen", "date" : "Saturday, Feb 18 2017", "time" : "14:30", "matchID" : 1090999},{ "team1" : "Hertha Berlin", "team2" : "Bayern Munich", "date" : "Saturday, Feb 18 2017", "time" : "14:30", "matchID" : 1091002},{ "team1" : "Hoffenheim", "team2" : "Darmstadt", "date" : "Saturday, Feb 18 2017", "time" : "14:30", "matchID" : 1090990},{ "team1" : "Hamburger SV", "team2" : "Freiburg", "date" : "Saturday, Feb 18 2017", "time" : "17:30", "matchID" : 1091008},{ "team1" : "Borussia M.Gladbach", "team2" : "RasenBallsport Leipzig", "date" : "Sunday, Feb 19 2017", "time" : "14:30", "matchID" : 1090997},{ "team1" : "FC Cologne", "team2" : "Schalke 04", "date" : "Sunday, Feb 19 2017", "time" : "16:30", "matchID" : 1091005}]